MANIFEST.in
README.md
requirements.txt
setup.py
keras_targeted_dropout/__init__.py
keras_targeted_dropout/backend.py
keras_targeted_dropout/targeted_dropout.py
keras_targeted_dropout.egg-info/PKG-INFO
keras_targeted_dropout.egg-info/SOURCES.txt
keras_targeted_dropout.egg-info/dependency_links.txt
keras_targeted_dropout.egg-info/requires.txt
keras_targeted_dropout.egg-info/top_level.txt
tests/__init__.py
tests/test_targeted_dropout.py