Metadata-Version: 2.1
Name: keras-targeted-dropout
Version: 0.5.0
Summary: Targeted dropout implemented in Keras
Home-page: https://github.com/CyberZHG/keras-targeted-dropout
Author: CyberZHG
Author-email: CyberZHG@gmail.com
License: MIT
Platform: UNKNOWN
Classifier: Programming Language :: Python :: 3.6
Classifier: License :: OSI Approved :: MIT License
Classifier: Operating System :: OS Independent
